{
  "nouns": {
    "A DDO": [
      {
        "end": 32,
        "start": 30,
        "type": "NP"
      }
    ],
    "It": [
      {
        "end": 45,
        "start": 44,
        "type": "NP"
      }
    ],
    "RECOMMENDED": [
      {
        "end": 47,
        "start": 46,
        "type": "NP"
      }
    ],
    "The key": [
      {
        "end": 55,
        "start": 53,
        "type": "NP"
      }
    ],
    "The rules": [
      {
        "end": 22,
        "start": 20,
        "type": "NP"
      }
    ],
    "The value": [
      {
        "end": 65,
        "start": 63,
        "type": "NP"
      }
    ],
    "Updated (Optional)\n\n\n    \n      Standard metadata": [
      {
        "end": 8,
        "start": 0,
        "type": "NP"
      }
    ],
    "a timestamp": [
      {
        "end": 14,
        "start": 12,
        "type": "NP"
      }
    ],
    "a updated timestamp": [
      {
        "end": 27,
        "start": 24,
        "type": "NP"
      }
    ],
    "an updated\ntimestamp": [
      {
        "end": 43,
        "start": 39,
        "type": "NP"
      }
    ],
    "identity records": [
      {
        "end": 11,
        "start": 9,
        "type": "NP"
      }
    ],
    "section": [
      {
        "end": 83,
        "start": 82,
        "type": "NP"
      }
    ],
    "the formatting rules": [
      {
        "end": 73,
        "start": 70,
        "type": "NP"
      }
    ],
    "the most recent change": [
      {
        "end": 19,
        "start": 15,
        "type": "NP"
      }
    ],
    "this key": [
      {
        "end": 68,
        "start": 66,
        "type": "NP"
      }
    ],
    "this property": [
      {
        "end": 51,
        "start": 49,
        "type": "NP"
      },
      {
        "end": 58,
        "start": 56,
        "type": "NP"
      }
    ],
    "zero or one property": [
      {
        "end": 38,
        "start": 34,
        "type": "NP"
      }
    ]
  },
  "terms": {
    "2016-10-17T02:41:00Z": [
      {
        "end": 101,
        "start": 96,
        "type": "DATE"
      }
    ],
    "3, 4": [
      {
        "end": 77,
        "start": 74,
        "type": "DATE"
      }
    ],
    "RECOMMENDED": [
      {
        "end": 47,
        "start": 46,
        "type": "ORG"
      }
    ],
    "one": [
      {
        "end": 37,
        "start": 36,
        "type": "CARDINAL"
      }
    ],
    "zero": [
      {
        "end": 35,
        "start": 34,
        "type": "CARDINAL"
      }
    ]
  },
  "types": {
    "CARDINAL": [
      {
        "end": 35,
        "label": "zero",
        "start": 34
      },
      {
        "end": 37,
        "label": "one",
        "start": 36
      }
    ],
    "DATE": [
      {
        "end": 77,
        "label": "3, 4",
        "start": 74
      },
      {
        "end": 101,
        "label": "2016-10-17T02:41:00Z",
        "start": 96
      }
    ],
    "ORG": [
      {
        "end": 47,
        "label": "RECOMMENDED",
        "start": 46
      }
    ]
  },
  "verbs": {
    "follow": 1,
    "format": 1,
    "have": 1,
    "include": 3,
    "represent": 1,
    "update": 5
  }
}
