{
  "2": {
    "(',', 'and')": 1,
    "('.', 'A')": 1,
    "('.', 'Clients')": 1,
    "('.', 'QR')": 1,
    "('.', 'The')": 1,
    "('11.1', 'Upper')": 1,
    "('2K', 'characters')": 1,
    "('4K', 'characters')": 1,
    "('A', 'future')": 1,
    "('Character', 'Length')": 1,
    "('Clients', 'using')": 1,
    "('DID', '.')": 1,
    "('DID', 'Character')": 1,
    "('DID', 'character')": 1,
    "('DIDs', ',')": 1,
    "('DIDs', 'intended')": 1,
    "('DIDs', 'will')": 1,
    "('Length', 'The')": 1,
    "('Limits', 'on')": 1,
    "('QR', 'codes')": 1,
    "('The', 'current')": 1,
    "('The', 'maximum')": 1,
    "('URL', 'length')": 1,
    "('Upper', 'Limits')": 1,
    "('a', 'DID')": 1,
    "('a', 'position')": 1,
    "('able', 'to')": 1,
    "('about', '2K')": 1,
    "('about', '4K')": 1,
    "('adding', 'state')": 1,
    "('and', 'some')": 1,
    "('be', 'able')": 1,
    "('be', 'responsible')": 1,
    "('by', 'adding')": 1,
    "('by', 'relying')": 1,
    "('can', 'handle')": 1,
    "('character', 'length')": 1,
    "('characters', '.')": 2,
    "('clients', 'by')": 1,
    "('codes', 'can')": 1,
    "('complicated', 'signature')": 1,
    "('costs', 'onto')": 1,
    "('current', 'specification')": 1,
    "('currently', 'about')": 1,
    "('does', 'not')": 1,
    "('externalities', '.')": 1,
    "('externalize', 'some')": 1,
    "('for', 'storing')": 1,
    "('for', 'temporary')": 1,
    "('future', 'version')": 1,
    "('handle', 'about')": 1,
    "('intended', 'for')": 1,
    "('interoperable', 'URL')": 1,
    "('into', 'DIDs')": 1,
    "('is', 'currently')": 1,
    "('length', 'is')": 1,
    "('length', 'of')": 1,
    "('length', 'to')": 1,
    "('limits', 'on')": 1,
    "('many', 'DIDs')": 1,
    "('maximum', 'interoperable')": 1,
    "('maximum', 'length')": 1,
    "('methods', 'would')": 1,
    "('minimize', 'externalities')": 1,
    "('more', 'complicated')": 1,
    "('not', 'take')": 1,
    "('of', 'a')": 1,
    "('of', 'their')": 1,
    "('of', 'this')": 1,
    "('on', 'DID')": 2,
    "('on', 'maximum')": 1,
    "('on', 'more')": 1,
    "('onto', 'clients')": 1,
    "('or', 'by')": 1,
    "('position', 'on')": 1,
    "('reasonable', 'limits')": 1,
    "('relying', 'on')": 1,
    "('responsible', 'for')": 1,
    "('schemes', 'or')": 1,
    "('set', 'reasonable')": 1,
    "('should', 'set')": 1,
    "('signature', 'schemes')": 1,
    "('some', 'methods')": 1,
    "('some', 'of')": 1,
    "('specification', 'does')": 1,
    "('specification', 'should')": 1,
    "('state', 'into')": 1,
    "('storing', 'many')": 1,
    "('take', 'a')": 1,
    "('temporary', 'use')": 1,
    "('their', 'costs')": 1,
    "('this', 'specification')": 1,
    "('to', 'externalize')": 1,
    "('to', 'minimize')": 1,
    "('use', '.')": 1,
    "('using', 'DIDs')": 1,
    "('version', 'of')": 1,
    "('will', 'be')": 1,
    "('would', 'be')": 1
  },
  "3": {
    "(',', 'and', 'some')": 1,
    "('.', 'A', 'future')": 1,
    "('.', 'Clients', 'using')": 1,
    "('.', 'QR', 'codes')": 1,
    "('.', 'The', 'maximum')": 1,
    "('11.1', 'Upper', 'Limits')": 1,
    "('2K', 'characters', '.')": 1,
    "('4K', 'characters', '.')": 1,
    "('A', 'future', 'version')": 1,
    "('Character', 'Length', 'The')": 1,
    "('Clients', 'using', 'DIDs')": 1,
    "('DID', '.', 'The')": 1,
    "('DID', 'Character', 'Length')": 1,
    "('DID', 'character', 'length')": 1,
    "('DIDs', ',', 'and')": 1,
    "('DIDs', 'intended', 'for')": 1,
    "('DIDs', 'will', 'be')": 1,
    "('Length', 'The', 'current')": 1,
    "('Limits', 'on', 'DID')": 1,
    "('QR', 'codes', 'can')": 1,
    "('The', 'current', 'specification')": 1,
    "('The', 'maximum', 'interoperable')": 1,
    "('URL', 'length', 'is')": 1,
    "('Upper', 'Limits', 'on')": 1,
    "('a', 'DID', '.')": 1,
    "('a', 'position', 'on')": 1,
    "('able', 'to', 'externalize')": 1,
    "('about', '2K', 'characters')": 1,
    "('about', '4K', 'characters')": 1,
    "('adding', 'state', 'into')": 1,
    "('and', 'some', 'methods')": 1,
    "('be', 'able', 'to')": 1,
    "('be', 'responsible', 'for')": 1,
    "('by', 'adding', 'state')": 1,
    "('by', 'relying', 'on')": 1,
    "('can', 'handle', 'about')": 1,
    "('character', 'length', 'to')": 1,
    "('characters', '.', 'Clients')": 1,
    "('characters', '.', 'QR')": 1,
    "('clients', 'by', 'relying')": 1,
    "('codes', 'can', 'handle')": 1,
    "('complicated', 'signature', 'schemes')": 1,
    "('costs', 'onto', 'clients')": 1,
    "('current', 'specification', 'does')": 1,
    "('currently', 'about', '2K')": 1,
    "('does', 'not', 'take')": 1,
    "('externalize', 'some', 'of')": 1,
    "('for', 'storing', 'many')": 1,
    "('for', 'temporary', 'use')": 1,
    "('future', 'version', 'of')": 1,
    "('handle', 'about', '4K')": 1,
    "('intended', 'for', 'temporary')": 1,
    "('interoperable', 'URL', 'length')": 1,
    "('into', 'DIDs', 'intended')": 1,
    "('is', 'currently', 'about')": 1,
    "('length', 'is', 'currently')": 1,
    "('length', 'of', 'a')": 1,
    "('length', 'to', 'minimize')": 1,
    "('limits', 'on', 'DID')": 1,
    "('many', 'DIDs', ',')": 1,
    "('maximum', 'interoperable', 'URL')": 1,
    "('maximum', 'length', 'of')": 1,
    "('methods', 'would', 'be')": 1,
    "('minimize', 'externalities', '.')": 1,
    "('more', 'complicated', 'signature')": 1,
    "('not', 'take', 'a')": 1,
    "('of', 'a', 'DID')": 1,
    "('of', 'their', 'costs')": 1,
    "('of', 'this', 'specification')": 1,
    "('on', 'DID', 'Character')": 1,
    "('on', 'DID', 'character')": 1,
    "('on', 'maximum', 'length')": 1,
    "('on', 'more', 'complicated')": 1,
    "('onto', 'clients', 'by')": 1,
    "('or', 'by', 'adding')": 1,
    "('position', 'on', 'maximum')": 1,
    "('reasonable', 'limits', 'on')": 1,
    "('relying', 'on', 'more')": 1,
    "('responsible', 'for', 'storing')": 1,
    "('schemes', 'or', 'by')": 1,
    "('set', 'reasonable', 'limits')": 1,
    "('should', 'set', 'reasonable')": 1,
    "('signature', 'schemes', 'or')": 1,
    "('some', 'methods', 'would')": 1,
    "('some', 'of', 'their')": 1,
    "('specification', 'does', 'not')": 1,
    "('specification', 'should', 'set')": 1,
    "('state', 'into', 'DIDs')": 1,
    "('storing', 'many', 'DIDs')": 1,
    "('take', 'a', 'position')": 1,
    "('temporary', 'use', '.')": 1,
    "('their', 'costs', 'onto')": 1,
    "('this', 'specification', 'should')": 1,
    "('to', 'externalize', 'some')": 1,
    "('to', 'minimize', 'externalities')": 1,
    "('use', '.', 'A')": 1,
    "('using', 'DIDs', 'will')": 1,
    "('version', 'of', 'this')": 1,
    "('will', 'be', 'responsible')": 1,
    "('would', 'be', 'able')": 1
  },
  "4": {
    "(',', 'and', 'some', 'methods')": 1,
    "('.', 'A', 'future', 'version')": 1,
    "('.', 'Clients', 'using', 'DIDs')": 1,
    "('.', 'QR', 'codes', 'can')": 1,
    "('.', 'The', 'maximum', 'interoperable')": 1,
    "('11.1', 'Upper', 'Limits', 'on')": 1,
    "('2K', 'characters', '.', 'QR')": 1,
    "('4K', 'characters', '.', 'Clients')": 1,
    "('A', 'future', 'version', 'of')": 1,
    "('Character', 'Length', 'The', 'current')": 1,
    "('Clients', 'using', 'DIDs', 'will')": 1,
    "('DID', '.', 'The', 'maximum')": 1,
    "('DID', 'Character', 'Length', 'The')": 1,
    "('DID', 'character', 'length', 'to')": 1,
    "('DIDs', ',', 'and', 'some')": 1,
    "('DIDs', 'intended', 'for', 'temporary')": 1,
    "('DIDs', 'will', 'be', 'responsible')": 1,
    "('Length', 'The', 'current', 'specification')": 1,
    "('Limits', 'on', 'DID', 'Character')": 1,
    "('QR', 'codes', 'can', 'handle')": 1,
    "('The', 'current', 'specification', 'does')": 1,
    "('The', 'maximum', 'interoperable', 'URL')": 1,
    "('URL', 'length', 'is', 'currently')": 1,
    "('Upper', 'Limits', 'on', 'DID')": 1,
    "('a', 'DID', '.', 'The')": 1,
    "('a', 'position', 'on', 'maximum')": 1,
    "('able', 'to', 'externalize', 'some')": 1,
    "('about', '2K', 'characters', '.')": 1,
    "('about', '4K', 'characters', '.')": 1,
    "('adding', 'state', 'into', 'DIDs')": 1,
    "('and', 'some', 'methods', 'would')": 1,
    "('be', 'able', 'to', 'externalize')": 1,
    "('be', 'responsible', 'for', 'storing')": 1,
    "('by', 'adding', 'state', 'into')": 1,
    "('by', 'relying', 'on', 'more')": 1,
    "('can', 'handle', 'about', '4K')": 1,
    "('character', 'length', 'to', 'minimize')": 1,
    "('characters', '.', 'Clients', 'using')": 1,
    "('characters', '.', 'QR', 'codes')": 1,
    "('clients', 'by', 'relying', 'on')": 1,
    "('codes', 'can', 'handle', 'about')": 1,
    "('complicated', 'signature', 'schemes', 'or')": 1,
    "('costs', 'onto', 'clients', 'by')": 1,
    "('current', 'specification', 'does', 'not')": 1,
    "('currently', 'about', '2K', 'characters')": 1,
    "('does', 'not', 'take', 'a')": 1,
    "('externalize', 'some', 'of', 'their')": 1,
    "('for', 'storing', 'many', 'DIDs')": 1,
    "('for', 'temporary', 'use', '.')": 1,
    "('future', 'version', 'of', 'this')": 1,
    "('handle', 'about', '4K', 'characters')": 1,
    "('intended', 'for', 'temporary', 'use')": 1,
    "('interoperable', 'URL', 'length', 'is')": 1,
    "('into', 'DIDs', 'intended', 'for')": 1,
    "('is', 'currently', 'about', '2K')": 1,
    "('length', 'is', 'currently', 'about')": 1,
    "('length', 'of', 'a', 'DID')": 1,
    "('length', 'to', 'minimize', 'externalities')": 1,
    "('limits', 'on', 'DID', 'character')": 1,
    "('many', 'DIDs', ',', 'and')": 1,
    "('maximum', 'interoperable', 'URL', 'length')": 1,
    "('maximum', 'length', 'of', 'a')": 1,
    "('methods', 'would', 'be', 'able')": 1,
    "('more', 'complicated', 'signature', 'schemes')": 1,
    "('not', 'take', 'a', 'position')": 1,
    "('of', 'a', 'DID', '.')": 1,
    "('of', 'their', 'costs', 'onto')": 1,
    "('of', 'this', 'specification', 'should')": 1,
    "('on', 'DID', 'Character', 'Length')": 1,
    "('on', 'DID', 'character', 'length')": 1,
    "('on', 'maximum', 'length', 'of')": 1,
    "('on', 'more', 'complicated', 'signature')": 1,
    "('onto', 'clients', 'by', 'relying')": 1,
    "('or', 'by', 'adding', 'state')": 1,
    "('position', 'on', 'maximum', 'length')": 1,
    "('reasonable', 'limits', 'on', 'DID')": 1,
    "('relying', 'on', 'more', 'complicated')": 1,
    "('responsible', 'for', 'storing', 'many')": 1,
    "('schemes', 'or', 'by', 'adding')": 1,
    "('set', 'reasonable', 'limits', 'on')": 1,
    "('should', 'set', 'reasonable', 'limits')": 1,
    "('signature', 'schemes', 'or', 'by')": 1,
    "('some', 'methods', 'would', 'be')": 1,
    "('some', 'of', 'their', 'costs')": 1,
    "('specification', 'does', 'not', 'take')": 1,
    "('specification', 'should', 'set', 'reasonable')": 1,
    "('state', 'into', 'DIDs', 'intended')": 1,
    "('storing', 'many', 'DIDs', ',')": 1,
    "('take', 'a', 'position', 'on')": 1,
    "('temporary', 'use', '.', 'A')": 1,
    "('their', 'costs', 'onto', 'clients')": 1,
    "('this', 'specification', 'should', 'set')": 1,
    "('to', 'externalize', 'some', 'of')": 1,
    "('to', 'minimize', 'externalities', '.')": 1,
    "('use', '.', 'A', 'future')": 1,
    "('using', 'DIDs', 'will', 'be')": 1,
    "('version', 'of', 'this', 'specification')": 1,
    "('will', 'be', 'responsible', 'for')": 1,
    "('would', 'be', 'able', 'to')": 1
  },
  "5": {
    "(',', 'and', 'some', 'methods', 'would')": 1,
    "('.', 'A', 'future', 'version', 'of')": 1,
    "('.', 'Clients', 'using', 'DIDs', 'will')": 1,
    "('.', 'QR', 'codes', 'can', 'handle')": 1,
    "('.', 'The', 'maximum', 'interoperable', 'URL')": 1,
    "('11.1', 'Upper', 'Limits', 'on', 'DID')": 1,
    "('2K', 'characters', '.', 'QR', 'codes')": 1,
    "('4K', 'characters', '.', 'Clients', 'using')": 1,
    "('A', 'future', 'version', 'of', 'this')": 1,
    "('Character', 'Length', 'The', 'current', 'specification')": 1,
    "('Clients', 'using', 'DIDs', 'will', 'be')": 1,
    "('DID', '.', 'The', 'maximum', 'interoperable')": 1,
    "('DID', 'Character', 'Length', 'The', 'current')": 1,
    "('DID', 'character', 'length', 'to', 'minimize')": 1,
    "('DIDs', ',', 'and', 'some', 'methods')": 1,
    "('DIDs', 'intended', 'for', 'temporary', 'use')": 1,
    "('DIDs', 'will', 'be', 'responsible', 'for')": 1,
    "('Length', 'The', 'current', 'specification', 'does')": 1,
    "('Limits', 'on', 'DID', 'Character', 'Length')": 1,
    "('QR', 'codes', 'can', 'handle', 'about')": 1,
    "('The', 'current', 'specification', 'does', 'not')": 1,
    "('The', 'maximum', 'interoperable', 'URL', 'length')": 1,
    "('URL', 'length', 'is', 'currently', 'about')": 1,
    "('Upper', 'Limits', 'on', 'DID', 'Character')": 1,
    "('a', 'DID', '.', 'The', 'maximum')": 1,
    "('a', 'position', 'on', 'maximum', 'length')": 1,
    "('able', 'to', 'externalize', 'some', 'of')": 1,
    "('about', '2K', 'characters', '.', 'QR')": 1,
    "('about', '4K', 'characters', '.', 'Clients')": 1,
    "('adding', 'state', 'into', 'DIDs', 'intended')": 1,
    "('and', 'some', 'methods', 'would', 'be')": 1,
    "('be', 'able', 'to', 'externalize', 'some')": 1,
    "('be', 'responsible', 'for', 'storing', 'many')": 1,
    "('by', 'adding', 'state', 'into', 'DIDs')": 1,
    "('by', 'relying', 'on', 'more', 'complicated')": 1,
    "('can', 'handle', 'about', '4K', 'characters')": 1,
    "('character', 'length', 'to', 'minimize', 'externalities')": 1,
    "('characters', '.', 'Clients', 'using', 'DIDs')": 1,
    "('characters', '.', 'QR', 'codes', 'can')": 1,
    "('clients', 'by', 'relying', 'on', 'more')": 1,
    "('codes', 'can', 'handle', 'about', '4K')": 1,
    "('complicated', 'signature', 'schemes', 'or', 'by')": 1,
    "('costs', 'onto', 'clients', 'by', 'relying')": 1,
    "('current', 'specification', 'does', 'not', 'take')": 1,
    "('currently', 'about', '2K', 'characters', '.')": 1,
    "('does', 'not', 'take', 'a', 'position')": 1,
    "('externalize', 'some', 'of', 'their', 'costs')": 1,
    "('for', 'storing', 'many', 'DIDs', ',')": 1,
    "('for', 'temporary', 'use', '.', 'A')": 1,
    "('future', 'version', 'of', 'this', 'specification')": 1,
    "('handle', 'about', '4K', 'characters', '.')": 1,
    "('intended', 'for', 'temporary', 'use', '.')": 1,
    "('interoperable', 'URL', 'length', 'is', 'currently')": 1,
    "('into', 'DIDs', 'intended', 'for', 'temporary')": 1,
    "('is', 'currently', 'about', '2K', 'characters')": 1,
    "('length', 'is', 'currently', 'about', '2K')": 1,
    "('length', 'of', 'a', 'DID', '.')": 1,
    "('length', 'to', 'minimize', 'externalities', '.')": 1,
    "('limits', 'on', 'DID', 'character', 'length')": 1,
    "('many', 'DIDs', ',', 'and', 'some')": 1,
    "('maximum', 'interoperable', 'URL', 'length', 'is')": 1,
    "('maximum', 'length', 'of', 'a', 'DID')": 1,
    "('methods', 'would', 'be', 'able', 'to')": 1,
    "('more', 'complicated', 'signature', 'schemes', 'or')": 1,
    "('not', 'take', 'a', 'position', 'on')": 1,
    "('of', 'a', 'DID', '.', 'The')": 1,
    "('of', 'their', 'costs', 'onto', 'clients')": 1,
    "('of', 'this', 'specification', 'should', 'set')": 1,
    "('on', 'DID', 'Character', 'Length', 'The')": 1,
    "('on', 'DID', 'character', 'length', 'to')": 1,
    "('on', 'maximum', 'length', 'of', 'a')": 1,
    "('on', 'more', 'complicated', 'signature', 'schemes')": 1,
    "('onto', 'clients', 'by', 'relying', 'on')": 1,
    "('or', 'by', 'adding', 'state', 'into')": 1,
    "('position', 'on', 'maximum', 'length', 'of')": 1,
    "('reasonable', 'limits', 'on', 'DID', 'character')": 1,
    "('relying', 'on', 'more', 'complicated', 'signature')": 1,
    "('responsible', 'for', 'storing', 'many', 'DIDs')": 1,
    "('schemes', 'or', 'by', 'adding', 'state')": 1,
    "('set', 'reasonable', 'limits', 'on', 'DID')": 1,
    "('should', 'set', 'reasonable', 'limits', 'on')": 1,
    "('signature', 'schemes', 'or', 'by', 'adding')": 1,
    "('some', 'methods', 'would', 'be', 'able')": 1,
    "('some', 'of', 'their', 'costs', 'onto')": 1,
    "('specification', 'does', 'not', 'take', 'a')": 1,
    "('specification', 'should', 'set', 'reasonable', 'limits')": 1,
    "('state', 'into', 'DIDs', 'intended', 'for')": 1,
    "('storing', 'many', 'DIDs', ',', 'and')": 1,
    "('take', 'a', 'position', 'on', 'maximum')": 1,
    "('temporary', 'use', '.', 'A', 'future')": 1,
    "('their', 'costs', 'onto', 'clients', 'by')": 1,
    "('this', 'specification', 'should', 'set', 'reasonable')": 1,
    "('to', 'externalize', 'some', 'of', 'their')": 1,
    "('use', '.', 'A', 'future', 'version')": 1,
    "('using', 'DIDs', 'will', 'be', 'responsible')": 1,
    "('version', 'of', 'this', 'specification', 'should')": 1,
    "('will', 'be', 'responsible', 'for', 'storing')": 1,
    "('would', 'be', 'able', 'to', 'externalize')": 1
  }
}
