{
  "nouns": {
    "The DID method specification": [
      {
        "end": 9,
        "start": 5,
        "type": "NP"
      }
    ],
    "a DID record": [
      {
        "end": 19,
        "start": 16,
        "type": "NP"
      }
    ],
    "a client": [
      {
        "end": 14,
        "start": 12,
        "type": "NP"
      }
    ],
    "all cryptographic operations": [
      {
        "end": 28,
        "start": 25,
        "type": "NP"
      }
    ],
    "control": [
      {
        "end": 34,
        "start": 33,
        "type": "NP"
      }
    ],
    "proof": [
      {
        "end": 32,
        "start": 31,
        "type": "NP"
      }
    ],
    "the target system": [
      {
        "end": 23,
        "start": 20,
        "type": "NP"
      }
    ]
  },
  "terms": {
    "DID": [
      {
        "end": 7,
        "start": 6,
        "type": "ORG"
      },
      {
        "end": 18,
        "start": 17,
        "type": "ORG"
      }
    ],
    "Update\n\n\n    \n      ": [
      {
        "end": 5,
        "start": 3,
        "type": "PERSON"
      }
    ]
  },
  "types": {
    "ORG": [
      {
        "end": 7,
        "label": "DID",
        "start": 6
      },
      {
        "end": 18,
        "label": "DID",
        "start": 17
      }
    ],
    "PERSON": [
      {
        "end": 5,
        "label": "Update\n\n\n    \n      ",
        "start": 3
      }
    ]
  },
  "verbs": {
    "establish": 1,
    "include": 1,
    "specify": 1,
    "update": 2
  }
}
